CHANGELOG.md
LICENSE.txt
MANIFEST.in
README.md
setup.py
COMSTABPY/__init__.py
COMSTABPY.egg-info/PKG-INFO
COMSTABPY.egg-info/SOURCES.txt
COMSTABPY.egg-info/dependency_links.txt
COMSTABPY.egg-info/top_level.txt
examples/column_plot.py
examples/comparison.py
examples/comstabpy.py
examples/create_datasets.py
examples/eveness.py
examples/main.py
examples/plot_csv.py
examples/plot_mean_biomass.py
examples/plot_mean_network.py
examples/plot_taylor.py
examples/plot_y_biomass.py
examples/prova.py
examples/sat_plot.py
examples/vertical_plot.py