Metadata-Version: 2.1
Name: COMSTABPY
Version: 0.1.2
Summary: COMSTABPY is an python package that contains basic functions to apply the unified framework for partitioning the drivers of stability of ecological communities
Home-page: https://github.com/gocchipintive/COMSTABPY
Author: Guido Occhipinti
Author-email: occhipinti.guido@gmail.com
License: MIT
Keywords: stability,ecology,biodiversity
Classifier: Development Status :: 5 - Production/Stable
Classifier: Intended Audience :: Science/Research
Classifier: Operating System :: MacOS
Classifier: License :: OSI Approved :: MIT License
Classifier: Programming Language :: Python :: 3
License-File: LICENSE.txt
